nwb_docutils/__init__.py
nwb_docutils/_version.py
nwb_docutils/compare-hdf5-files.ipynb
nwb_docutils/generate_format_docs.py
nwb_docutils/init_sphinx_extension_doc.py
nwb_docutils/sg_prototype.py
nwb_docutils/doctools/__init__.py
nwb_docutils/doctools/output.py
nwb_docutils/doctools/render.py
nwb_docutils/doctools/renderrst.py
nwb_docutils/doctools/rst.py
nwb_docutils-0.3.1.dist-info/METADATA
nwb_docutils-0.3.1.dist-info/WHEEL
nwb_docutils-0.3.1.dist-info/entry_points.txt
nwb_docutils-0.3.1.dist-info/top_level.txt
nwb_docutils-0.3.1.dist-info/RECORD
