Metadata-Version: 2.1
Name: nwb-docutils
Version: 0.3.1
Summary: Collection of CLIs, scripts and modules useful to generate the NWB documentation
Home-page: https://github.com/NeurodataWithoutBorders/nwb-docutils
Author: Oliver Ruebel
Author-email: oruebel@lbl.gov
License: BSD
Keywords: Neuroscience python HDF HDF5 cross-platform open-data data-format open-source open-science reproducible-research PyNWB NWB NWB:N NeurodataWithoutBorders
Platform: UNKNOWN
Classifier: Programming Language :: Python
Classifier: Programming Language :: Python :: 3.5
Classifier: Programming Language :: Python :: 3.6
Classifier: Programming Language :: Python :: 3.7
Classifier: License :: OSI Approved :: BSD License
Classifier: Development Status :: 2 - Pre-Alpha
Classifier: Intended Audience :: Developers
Classifier: Intended Audience :: Science/Research
Classifier: Operating System :: Microsoft :: Windows
Classifier: Operating System :: MacOS
Classifier: Operating System :: Unix
Classifier: Topic :: Documentation :: Sphinx
Requires-Dist: matplotlib
Requires-Dist: networkx
Requires-Dist: pynwb
Requires-Dist: hdmf
Requires-Dist: pillow
Requires-Dist: sphinx (==1.6.5)
Requires-Dist: sphinx-gallery
Requires-Dist: sphinx-rtd-theme
